pytest_frozen_uuids/__main__.py
pytest_frozen_uuids/config.py
pytest_frozen_uuids/generators.py
pytest_frozen_uuids/utils.py
pytest_frozen_uuids-0.3.5.dist-info/LICENSE
pytest_frozen_uuids-0.3.5.dist-info/METADATA
pytest_frozen_uuids-0.3.5.dist-info/WHEEL
pytest_frozen_uuids-0.3.5.dist-info/entry_points.txt
pytest_frozen_uuids-0.3.5.dist-info/top_level.txt
pytest_frozen_uuids-0.3.5.dist-info/RECORD
