Metadata-Version: 2.1
Name: pytest-frozen-uuids
Version: 0.3.5
Summary: Deterministically frozen UUID's for your tests
Home-page: https://github.com/simonwahlgren/pytest-frozen-uuids
Author: Simon Wahlgren
Author-email: simon.wahlgren@gmail.com
License: MIT
Platform: UNKNOWN
Classifier: Framework :: Pytest
Classifier: Topic :: Software Development :: Testing
Classifier: Programming Language :: Python :: 3
Requires-Python: >=3.6
License-File: LICENSE
Requires-Dist: pytest (>=3.0)
